dcutils/__init__.py
dcutils/bigquery.py
dcutils/copy_batch.py
dcutils/triggers.py
dcutils-0.30.dist-info/LICENSE
dcutils-0.30.dist-info/METADATA
dcutils-0.30.dist-info/WHEEL
dcutils-0.30.dist-info/top_level.txt
dcutils-0.30.dist-info/RECORD
