Metadata-Version: 2.1
Name: dcutils
Version: 0.30
Summary: A simple package for data center utilities
Home-page: https://github.com/K-Winkles/dcutils
Author: Kiana Alessandra V. Villaera
Author-email: kiana.villaera@senti.com.ph
License: UNKNOWN
Platform: UNKNOWN
Classifier: Programming Language :: Python :: 3
Classifier: License :: OSI Approved :: MIT License
Classifier: Operating System :: OS Independent
Requires-Python: >=3.6
